EDM_pybind.cp37-win_amd64.pyd
EDM/EDM.py
EDM/__init__.py
EDM/data/CCM_anch_sst_cppEDM_valid.csv
EDM/data/Multiview_combos_valid.csv
EDM/data/Multiview_pred_valid.csv
EDM/data/Smap_circle_pyEDM.csv
EDM/data/Smap_embd_block_3sp_pyEDM.csv
EDM/data/Smplx_E3_block_3sp_pyEDM.csv
EDM/data/Smplx_embd_block_3sp_pyEDM.csv
EDM/data/TentMapNoise_rEDM.csv
EDM/data/TentMap_rEDM.csv
EDM/data/block_3sp.csv
EDM/data/circle.csv
EDM/data/circle_noise.csv
EDM/data/sardine_anchovy_sst.csv
EDM/tests/examples.py
EDM/tests/tests.py
EDM_SugiharaLab-0.1.3.post2.dist-info/LICENSE
EDM_SugiharaLab-0.1.3.post2.dist-info/METADATA
EDM_SugiharaLab-0.1.3.post2.dist-info/WHEEL
EDM_SugiharaLab-0.1.3.post2.dist-info/top_level.txt
EDM_SugiharaLab-0.1.3.post2.dist-info/RECORD
