Metadata-Version: 2.1
Name: EDM-SugiharaLab
Version: 0.1.3-2
Summary: Python wrapper for cppEDM using pybind11
Home-page: https://github.com/SugiharaLab/pyEDM
Author: Joseph Park & Cameron Smith
Author-email: Sugihara.Lab@gmail.com
License: Copyright 2019 The Regents of the University of California.
Platform: UNKNOWN
Requires-Python: >=3
Requires-Dist: pybind11 (>=2.2)
Requires-Dist: pandas (>=0.20.3)
Requires-Dist: matplotlib (>=2.2)
